Metadata-Version: 2.1
Name: odoo-addon-stock_move_source_relocate
Version: 18.0.1.0.0.3
Requires-Python: >=3.10
Requires-Dist: odoo-addon-stock_location_is_sublocation==18.0.*
Requires-Dist: odoo-addon-stock_route_location_source==18.0.*
Requires-Dist: odoo==18.0.*
Summary: Change source location of unavailable moves
Home-page: https://github.com/OCA/stock-logistics-workflow
License: AGPL-3
Author: Camptocamp, BCIM, Odoo Community Association (OCA)
Author-email: support@odoo-community.org
Classifier: Programming Language :: Python
Classifier: Framework :: Odoo
Classifier: Framework :: Odoo :: 18.0
Classifier: License :: OSI Approved :: GNU Affero General Public License v3
Classifier: Development Status :: 4 - Beta
